jiuwen/__init__.py
jiuwen/agent/__init__.py
jiuwen/agent/react_agent.py
jiuwen/agent/workflow_agent.py
jiuwen/agent/common/__init__.py
jiuwen/agent/common/enum.py
jiuwen/agent/common/schema.py
jiuwen/agent/config/__init__.py
jiuwen/agent/config/base.py
jiuwen/agent/config/react_config.py
jiuwen/agent/config/workflow_config.py
jiuwen/agent/skills/__init__.py
jiuwen/agent_builder/prompt_builder/__init__.py
jiuwen/agent_builder/prompt_builder/tune/joint_evaluator.py
jiuwen/agent_builder/prompt_builder/tune/joint_optimizer.py
jiuwen/agent_builder/prompt_builder/tune/base/case.py
jiuwen/agent_builder/prompt_builder/tune/base/constant.py
jiuwen/agent_builder/prompt_builder/tune/base/context_manager.py
jiuwen/agent_builder/prompt_builder/tune/base/exception.py
jiuwen/agent_builder/prompt_builder/tune/base/utils.py
jiuwen/agent_builder/prompt_builder/tune/common/exception.py
jiuwen/agent_builder/prompt_builder/tune/common/singleton.py
jiuwen/core/__init__.py
jiuwen/core/agent/__init__.py
jiuwen/core/agent/agent.py
jiuwen/core/agent/controller/__init__.py
jiuwen/core/agent/controller/base.py
jiuwen/core/agent/controller/react_controller.py
jiuwen/core/agent/controller/workflow_controller.py
jiuwen/core/agent/handler/__init__.py
jiuwen/core/agent/handler/base.py
jiuwen/core/agent/state_machine/__init__.py
jiuwen/core/agent/state_machine/react_state_machine.py
jiuwen/core/agent/state_machine/workflow_agent_state_machine.py
jiuwen/core/agent/task/__init__.py
jiuwen/core/agent/task/sub_task.py
jiuwen/core/agent/task/task.py
jiuwen/core/agent/task/task_context.py
jiuwen/core/agent/task/task_manager.py
jiuwen/core/common/constants/__init__.py
jiuwen/core/common/constants/component.py
jiuwen/core/common/constants/constant.py
jiuwen/core/common/enum/__init__.py
jiuwen/core/common/enum/enum.py
jiuwen/core/common/exception/__init__.py
jiuwen/core/common/exception/exception.py
jiuwen/core/common/exception/status_code.py
jiuwen/core/common/logging/__init__.py
jiuwen_opensource-0.1.0.dist-info/LICENSE
jiuwen_opensource-0.1.0.dist-info/METADATA
jiuwen_opensource-0.1.0.dist-info/WHEEL
jiuwen_opensource-0.1.0.dist-info/top_level.txt
jiuwen_opensource-0.1.0.dist-info/RECORD
