Metadata-Version: 2.1
Name: jiuwen-opensource
Version: 0.1.0
Summary: Add your description here
Requires-Python: >=3.11
License-File: LICENSE
Requires-Dist: aiohttp ==3.11.12
Requires-Dist: langgraph ==0.6.3
Requires-Dist: mcp ==1.12.2
Requires-Dist: pydantic ==2.11.5
Requires-Dist: python-dateutil ==2.9.0.post0
Requires-Dist: sqlalchemy ==2.0.41
Requires-Dist: cacheout ==0.16.0
